owl/__init__.py
owl/core/eda.py
owl/core/utils.py
owl/detection/tools.py
owl_python-1.0.6.dist-info/LICENSE
owl_python-1.0.6.dist-info/METADATA
owl_python-1.0.6.dist-info/WHEEL
owl_python-1.0.6.dist-info/top_level.txt
owl_python-1.0.6.dist-info/RECORD
